c3voc.py
epgdb.py
e2voc-0.1.1.dist-info/entry_points.txt
e2voc-0.1.1.dist-info/LICENSE
e2voc-0.1.1.dist-info/WHEEL
e2voc-0.1.1.dist-info/METADATA
e2voc-0.1.1.dist-info/RECORD
