Metadata-Version: 2.1
Name: e2voc
Version: 0.1.1
Summary: 
Home-page: https://github.com/mtdcr/e2voc
License: MIT
Author: Andreas Oberritter
Author-email: obi@saftware.de
Requires-Python: >=2.7, !=3.0.*, !=3.1.*, !=3.2.*, !=3.3.*, !=3.4.*, !=3.5.*
Classifier: License :: OSI Approved :: MIT License
Classifier: Programming Language :: Python :: 2
Classifier: Programming Language :: Python :: 2.7
Classifier: Programming Language :: Python :: 3
Classifier: Programming Language :: Python :: 3.10
Classifier: Programming Language :: Python :: 3.6
Classifier: Programming Language :: Python :: 3.7
Classifier: Programming Language :: Python :: 3.8
Classifier: Programming Language :: Python :: 3.9
Requires-Dist: requests (>=2,<3)
Project-URL: Repository, https://github.com/mtdcr/e2voc
